extended_sklearn_metrics/__init__.py
extended_sklearn_metrics/_plotting_backend.py
extended_sklearn_metrics/_validation.py
extended_sklearn_metrics/classification_evaluation.py
extended_sklearn_metrics/comprehensive_evaluation.py
extended_sklearn_metrics/evaluation_reporting.py
extended_sklearn_metrics/model_evaluation.py
extended_sklearn_metrics/residual_diagnostics.py
extended_sklearn_metrics/roc_auc_analysis.py
extended_sklearn_metrics/visualizations.py
extended_sklearn_metrics/visualizations/__init__.py
extended_sklearn_metrics/visualizations/_base.py
extended_sklearn_metrics/visualizations/comprehensive.py
extended_sklearn_metrics/visualizations/fairness.py
extended_sklearn_metrics/visualizations/performance.py
extended_sklearn_metrics/visualizations/residuals.py
extended_sklearn_metrics/visualizations/roc_curves.py
extended_sklearn_metrics-0.4.0.dist-info/licenses/LICENSE
tests/__init__.py
tests/run_tests.py
tests/test_classification_evaluation.py
tests/test_custom_thresholds.py
tests/test_input_validation.py
tests/test_model_evaluation.py
tests/test_pipeline_support.py
tests/test_residual_diagnostics.py
tests/test_roc_auc_analysis.py
extended_sklearn_metrics-0.4.0.dist-info/METADATA
extended_sklearn_metrics-0.4.0.dist-info/WHEEL
extended_sklearn_metrics-0.4.0.dist-info/top_level.txt
extended_sklearn_metrics-0.4.0.dist-info/RECORD
