Metadata-Version: 2.4
Name: extended-sklearn-metrics
Version: 0.4.0
Summary: Comprehensive evaluation library for scikit-learn models with advanced metrics, custom thresholds, and visualizations
Home-page: https://github.com/subashanannair/extended-sklearn-metrics
Author: Subashanan Nair
Author-email: Subashanan Nair <subashnair12@gmail.com>
License: MIT
Project-URL: Homepage, https://github.com/subashanannair/extended-sklearn-metrics
Project-URL: Bug Tracker, https://github.com/subashanannair/extended-sklearn-metrics/issues
Classifier: Programming Language :: Python :: 3
Classifier: Operating System :: OS Independent
Requires-Python: >=3.8
License-File: LICENSE
Requires-Dist: numpy>=1.24.0
Requires-Dist: pandas>=2.0.0
Requires-Dist: scikit-learn>=1.3.0
Dynamic: author
Dynamic: home-page
Dynamic: license-file
Dynamic: requires-python
